nimesh/__init__.py
nimesh/asarray.py
nimesh/core.py
nimesh/mixins.py
nimesh/io/__init__.py
nimesh/io/freesurfer.py
nimesh/io/gifti.py
nimesh-0.0.1.dist-info/METADATA
nimesh-0.0.1.dist-info/RECORD
nimesh-0.0.1.dist-info/WHEEL
nimesh-0.0.1.dist-info/top_level.txt
